mcl_google_cloud_bigquery/__init__.py
mcl_google_cloud_bigquery/__main__.py
mcl_google_cloud_bigquery/bigquery.py
mcl_google_cloud_bigquery/config.py
mcl_google_cloud_bigquery/greetings.py
mcl_google_cloud_bigquery/logging.py
mcl_google_cloud_bigquery-2022.5.23.18.23.25.dist-info/LICENSE
mcl_google_cloud_bigquery-2022.5.23.18.23.25.dist-info/WHEEL
mcl_google_cloud_bigquery-2022.5.23.18.23.25.dist-info/METADATA
mcl_google_cloud_bigquery-2022.5.23.18.23.25.dist-info/RECORD
