Metadata-Version: 2.1
Name: mcl_google_cloud_bigquery
Version: 2022.5.23.18.23.25
Summary: The mcl_google_cloud_bigquery package.
Author-email: Manuel Castillo-Lopez <manucalop@gmail.com>
Requires-Python: >=3.6
Classifier: License :: OSI Approved :: MIT License
Requires-Dist: pyyaml
Requires-Dist: google-cloud-bigquery
Requires-Dist: pandas
Requires-Dist: pandas-gbq
Project-URL: Home, https://github.com/manucalop/mcl_google_cloud_bigquery
